{
"-MVsZc13JBffO_rHNGm7":{"uid":"JuppZJLbLrWlA0YbSTinzuHypEP2","airportImage":"http://dummyimage.com/300x300.png/5fa2dd/ffffff","airportLocation":"Novoarkhanhel’s’k","airportName":"Triaminic"},
"-MVsZc15r1_1R1JGuOqL":{"uid":"JuppZJLbLrWlA0YbSTinzuHypEP2","airportImage":"http://dummyimage.com/300x300.png/ff4444/ffffff","airportLocation":"La Maná","airportName":"PARAID Extra Strength Menthol Pain Relief Sleeve KNEE Large Ankles Elbows"},
"-MVsZc17j78ZxX-t398j":{"uid":"JuppZJLbLrWlA0YbSTinzuHypEP2","airportImage":"http://dummyimage.com/300x300.png/ff4444/ffffff","airportLocation":"Shibi","airportName":"Morphine Sulfate"},
"-MVsZc19CJZAZKwU-AXz":{"uid":"JuppZJLbLrWlA0YbSTinzuHypEP2","airportImage":"http://dummyimage.com/300x300.png/cc0000/ffffff","airportLocation":"Hanghuadian","airportName":"Rite Aid Anti-Cavity, Anti-Gingivitis"},
"-MVsZc1AfDpUWIr9l7PM":{"uid":"JuppZJLbLrWlA0YbSTinzuHypEP2","airportImage":"http://dummyimage.com/300x300.png/dddddd/000000","airportLocation":"Vishnyeva","airportName":"Piperacillin and Tazobactam"},
"-MVsZc1D8VCnbiPBqHNY":{"uid":"JuppZJLbLrWlA0YbSTinzuHypEP2","airportImage":"http://dummyimage.com/300x300.png/cc0000/ffffff","airportLocation":"Weiwangzhuang","airportName":"FENOFIBRATE"},
"-MVsZc1FZJqMq_IELI9s":{"uid":"JuppZJLbLrWlA0YbSTinzuHypEP2","airportImage":"http://dummyimage.com/300x300.png/cc0000/ffffff","airportLocation":"Talanga","airportName":"Home Health Psoriasis"},
"-MVsZc1GM7QWBRQGXTgP":{"uid":"JuppZJLbLrWlA0YbSTinzuHypEP2","airportImage":"http://dummyimage.com/300x300.png/5fa2dd/ffffff","airportLocation":"Volovets","airportName":"care one cold multi symptom"},
"-MVsZc1Idu_eKqSoMXJ8":{"uid":"JuppZJLbLrWlA0YbSTinzuHypEP2","airportImage":"http://dummyimage.com/300x300.png/cc0000/ffffff","airportLocation":"Tuscaloosa","airportName":"TRIMO SAN"},
"-MVsZc1JyQ5dl1cdivBS":{"uid":"JuppZJLbLrWlA0YbSTinzuHypEP2","airportImage":"http://dummyimage.com/300x300.png/5fa2dd/ffffff","airportLocation":"Kayapa","airportName":"benzonatate"}
}