{
"-MVs_0C7HC0ckxpVEbFx":{"uid":"JuppZJLbLrWlA0YbSTinzuHypEP2","foodImage":"http://dummyimage.com/300x300.png/5fa2dd/ffffff","foodName":"Black-winged stilt","foodPrice":"$8.09"},
"-MVs_0C9IyUcqnlJvCzC":{"uid":"JuppZJLbLrWlA0YbSTinzuHypEP2","foodImage":"http://dummyimage.com/300x300.png/dddddd/000000","foodName":"Common rhea","foodPrice":"$8.79"},
"-MVs_0CCHoGAf0KdS8Pn":{"uid":"JuppZJLbLrWlA0YbSTinzuHypEP2","foodImage":"http://dummyimage.com/300x300.png/ff4444/ffffff","foodName":"Common ringtail","foodPrice":"$2.53"},
"-MVs_0CE0Y0BbCPdgQRB":{"uid":"JuppZJLbLrWlA0YbSTinzuHypEP2","foodImage":"http://dummyimage.com/300x300.png/cc0000/ffffff","foodName":"Yellow-crowned night heron","foodPrice":"$7.66"},
"-MVs_0CGggHv_rG8ZgdC":{"uid":"JuppZJLbLrWlA0YbSTinzuHypEP2","foodImage":"http://dummyimage.com/300x300.png/dddddd/000000","foodName":"Constrictor, eastern boa","foodPrice":"$8.45"},
"-MVs_0CJ9vnU_z06rSk5":{"uid":"JuppZJLbLrWlA0YbSTinzuHypEP2","foodImage":"http://dummyimage.com/300x300.png/dddddd/000000","foodName":"Spotted-tailed quoll","foodPrice":"$2.10"},
"-MVs_0CL4F0I4g4QFU-Y":{"uid":"JuppZJLbLrWlA0YbSTinzuHypEP2","foodImage":"http://dummyimage.com/300x300.png/5fa2dd/ffffff","foodName":"Coqui francolin","foodPrice":"$8.11"},
"-MVs_0COi5aSwnIvW_kT":{"uid":"JuppZJLbLrWlA0YbSTinzuHypEP2","foodImage":"http://dummyimage.com/300x300.png/dddddd/000000","foodName":"Badger, american","foodPrice":"$0.07"},
"-MVs_0CQuDnEadQigeKV":{"uid":"JuppZJLbLrWlA0YbSTinzuHypEP2","foodImage":"http://dummyimage.com/300x300.png/cc0000/ffffff","foodName":"Common wolf","foodPrice":"$9.08"},
"-MVs_0CSUCwrgsf42ipF":{"uid":"JuppZJLbLrWlA0YbSTinzuHypEP2","foodImage":"http://dummyimage.com/300x300.png/cc0000/ffffff","foodName":"Lion, southern sea","foodPrice":"$7.72"}
}